chaosmonkey/__init__.py
chaosmonkey/api/__init__.py
chaosmonkey/api/api_errors.py
chaosmonkey/api/app.py
chaosmonkey/api/attacks_blueprint.py
chaosmonkey/api/executors_blueprint.py
chaosmonkey/api/planners_blueprint.py
chaosmonkey/api/plans_blueprint.py
chaosmonkey/api/request_validator.py
chaosmonkey/api/utils.py
chaosmonkey/attacks/__init__.py
chaosmonkey/attacks/attack.py
chaosmonkey/attacks/executor.py
chaosmonkey/cm/__init__.py
chaosmonkey/cm/cm.py
chaosmonkey/dal/__init__.py
chaosmonkey/dal/cme_sqlalchemy_store.py
chaosmonkey/dal/database.py
chaosmonkey/dal/executor_model.py
chaosmonkey/dal/plan_model.py
chaosmonkey/drivers/__init__.py
chaosmonkey/drivers/ec2_driver.py
chaosmonkey/engine/__init__.py
chaosmonkey/engine/app.py
chaosmonkey/engine/cme_manager.py
chaosmonkey/engine/scheduler.py
chaosmonkey/modules/__init__.py
chaosmonkey/modules/module_store.py
chaosmonkey/planners/__init__.py
chaosmonkey/planners/planner.py
chaosmonkey-1.1.0.dist-info/DESCRIPTION.rst
chaosmonkey-1.1.0.dist-info/METADATA
chaosmonkey-1.1.0.dist-info/RECORD
chaosmonkey-1.1.0.dist-info/WHEEL
chaosmonkey-1.1.0.dist-info/entry_points.txt
chaosmonkey-1.1.0.dist-info/metadata.json
chaosmonkey-1.1.0.dist-info/top_level.txt
test/__init__.py
test/attacks/__init__.py
test/attacks/attack1.py
test/attacks/attack2.py
test/attacks/required_schema.py
test/planners/__init__.py
test/planners/planner1.py
test/planners/planner2.py
test/planners/required_schema.py
test/planners/two_executors.py
test/unit/__init__.py
test/unit/conftest.py
test/unit/chaosmonkey/__init__.py
test/unit/chaosmonkey/api/__init__.py
test/unit/chaosmonkey/api/attacks_blueprint_test.py
test/unit/chaosmonkey/api/executors_blueprint_test.py
test/unit/chaosmonkey/api/planners_blueprint_test.py
test/unit/chaosmonkey/api/plans_blueprint_test.py
test/unit/chaosmonkey/modules/__init__.py
test/unit/chaosmonkey/modules/module_store_test.py
