Metadata-Version: 2.0
Name: chaosmonkey
Version: 1.1.0
Summary: A Chaos Engineering swiss army knife
Home-page: https://github.com/BBVA/chaos-monkey-engine
Author: BBVALabs
Author-email: UNKNOWN
License: UNKNOWN
Platform: UNKNOWN
Requires-Dist: SQLAlchemy (==1.1.5)
Requires-Dist: apache-libcloud (==1.5.0)
Requires-Dist: apscheduler (==3.3.1)
Requires-Dist: arrow (==0.10.0)
Requires-Dist: click (==6.7)
Requires-Dist: flask (==0.12)
Requires-Dist: flask-cors (==3.0.2)
Requires-Dist: flask-hal-bbva (==1.0.5)
Requires-Dist: flask-sqlalchemy (==2.1)
Requires-Dist: gevent (==1.2.1)
Requires-Dist: jsonschema (==2.6.0)
Requires-Dist: paramiko (==2.1.1)
Requires-Dist: requests (==2.13.0)
